nonebot_plugin_NobleDuel/__init__.py
nonebot_plugin_NobleDuel/config.py
nonebot_plugin_nobleduel-0.3.19.dist-info/METADATA
nonebot_plugin_nobleduel-0.3.19.dist-info/WHEEL
nonebot_plugin_nobleduel-0.3.19.dist-info/top_level.txt
nonebot_plugin_nobleduel-0.3.19.dist-info/RECORD
