Metadata-Version: 2.4
Name: nonebot_plugin_NobleDuel
Version: 0.3.19
Summary: 一个nonebot2插件，包含了多种玩法
Author: cikasaaa
Author-email: 2058550737@qq.com
Classifier: Development Status :: 4 - Beta
Classifier: Framework :: AsyncIO
Classifier: Programming Language :: Python :: 3
Classifier: Programming Language :: Python :: 3.8
Classifier: Programming Language :: Python :: 3.9
Classifier: Programming Language :: Python :: 3.10
Classifier: Programming Language :: Python :: 3.11
Classifier: Topic :: Communications :: Chat
Classifier: Topic :: Games/Entertainment
Requires-Python: >=3.9
Requires-Dist: nonebot2>=2.3.0
Requires-Dist: nonebot-adapter-onebot>=2.0.0
Requires-Dist: nonebot-plugin-alconna>=0.55.0
Requires-Dist: nonebot-plugin-apscheduler>=0.5.0
Requires-Dist: nonebot_plugin_localstore>=0.7.0
Dynamic: author
Dynamic: author-email
Dynamic: classifier
Dynamic: requires-dist
Dynamic: requires-python
Dynamic: summary
